Metadata-Version: 2.2
Name: proxmox_client
Version: 1.0.1
Summary: Python client for Proxmox
Home-page: https://github.com/ErilovNikita/proxmox-client
Author-email: minitwiks@gmail.com
License: MIT
License-File: LICENSE
Requires-Dist: requests==2.32.3
Requires-Dist: urllib3==2.2.3
Requires-Dist: pydantic==2.9.2
Dynamic: author-email
Dynamic: description
Dynamic: description-content-type
Dynamic: home-page
Dynamic: license
Dynamic: requires-dist
Dynamic: summary
